adjutant_ui/__init__.py
adjutant_ui/karma.conf.js
adjutant_ui/version.py
adjutant_ui/api/__init__.py
adjutant_ui/api/adjutant.py
adjutant_ui/content/__init__.py
adjutant_ui/content/default/__init__.py
adjutant_ui/content/default/panel.py
adjutant_ui/content/default/templates/default/base.html
adjutant_ui/content/email/__init__.py
adjutant_ui/content/email/forms.py
adjutant_ui/content/email/panel.py
adjutant_ui/content/email/urls.py
adjutant_ui/content/email/views.py
adjutant_ui/content/email/templates/email/_change.html
adjutant_ui/content/email/templates/email/change.html
adjutant_ui/content/forgot_password/__init__.py
adjutant_ui/content/forgot_password/forms.py
adjutant_ui/content/forgot_password/panel.py
adjutant_ui/content/forgot_password/urls.py
adjutant_ui/content/forgot_password/views.py
adjutant_ui/content/forgot_password/templates/auth/_login_page.html
adjutant_ui/content/forgot_password/templates/forgot_password/_forgot_password_form.html
adjutant_ui/content/forgot_password/templates/forgot_password/_index.html
adjutant_ui/content/forgot_password/templates/forgot_password/_sent.html
adjutant_ui/content/forgot_password/templates/forgot_password/_sent_text.html
adjutant_ui/content/forgot_password/templates/forgot_password/index.html
adjutant_ui/content/forgot_password/templates/forgot_password/sent.html
adjutant_ui/content/notifications/__init__.py
adjutant_ui/content/notifications/panel.py
adjutant_ui/content/notifications/tables.py
adjutant_ui/content/notifications/tabs.py
adjutant_ui/content/notifications/urls.py
adjutant_ui/content/notifications/views.py
adjutant_ui/content/notifications/templates/notifications/detail.html
adjutant_ui/content/notifications/templates/notifications/index.html
adjutant_ui/content/notifications/templates/notifications/table_override.html
adjutant_ui/content/project_users/__init__.py
adjutant_ui/content/project_users/forms.py
adjutant_ui/content/project_users/panel.py
adjutant_ui/content/project_users/tables.py
adjutant_ui-11.0.0.dist-info/AUTHORS
adjutant_ui-11.0.0.dist-info/LICENSE
adjutant_ui-11.0.0.dist-info/METADATA
adjutant_ui-11.0.0.dist-info/WHEEL
adjutant_ui-11.0.0.dist-info/pbr.json
adjutant_ui-11.0.0.dist-info/top_level.txt
adjutant_ui-11.0.0.dist-info/RECORD
